greek_utils-0.2.dist-info/DESCRIPTION.rst
greek_utils-0.2.dist-info/METADATA
greek_utils-0.2.dist-info/RECORD
greek_utils-0.2.dist-info/WHEEL
greek_utils-0.2.dist-info/metadata.json
greek_utils-0.2.dist-info/top_level.txt
greekutils/__init__.py
greekutils/beta2unicode.py
greekutils/booknames.py
greekutils/trie.py
greekutils/trigrams.py
greekutils/verse_ref.py
