Metadata-Version: 2.0
Name: greek-utils
Version: 0.2
Summary: various utilities for processing Ancient Greek
Home-page: http://github.com/jtauber/greek-utils
Author: James Tauber
Author-email: jtauber@jtauber.com
License: MIT
Platform: UNKNOWN
Classifier: Development Status :: 3 - Alpha
Classifier: License :: OSI Approved :: MIT License
Classifier: Programming Language :: Python :: 3.3
Classifier: Programming Language :: Python :: 3.4
Classifier: Programming Language :: Python :: 3.5
Classifier: Topic :: Text Processing
Classifier: Topic :: Text Processing :: Linguistic
Classifier: Topic :: Utilities
